jupyterlab_markdown_insert_content_extension/__init__.py
jupyterlab_markdown_insert_content_extension/_version.py
jupyterlab_markdown_insert_content_extension-1.1.15.data/data/share/jupyter/labextensions/jupyterlab_markdown_insert_content_extension/package.json
jupyterlab_markdown_insert_content_extension-1.1.15.data/data/share/jupyter/labextensions/jupyterlab_markdown_insert_content_extension/schemas/jupyterlab_markdown_insert_content_extension/package.json.orig
jupyterlab_markdown_insert_content_extension-1.1.15.data/data/share/jupyter/labextensions/jupyterlab_markdown_insert_content_extension/schemas/jupyterlab_markdown_insert_content_extension/plugin.json
jupyterlab_markdown_insert_content_extension-1.1.15.data/data/share/jupyter/labextensions/jupyterlab_markdown_insert_content_extension/static/509.dfaaaac2a5516dde650c.js
jupyterlab_markdown_insert_content_extension-1.1.15.data/data/share/jupyter/labextensions/jupyterlab_markdown_insert_content_extension/static/728.1fca5e64a579e80f94a6.js
jupyterlab_markdown_insert_content_extension-1.1.15.data/data/share/jupyter/labextensions/jupyterlab_markdown_insert_content_extension/static/remoteEntry.7aca275afe97a38f9c5b.js
jupyterlab_markdown_insert_content_extension-1.1.15.data/data/share/jupyter/labextensions/jupyterlab_markdown_insert_content_extension/static/style.js
jupyterlab_markdown_insert_content_extension-1.1.15.data/data/share/jupyter/labextensions/jupyterlab_markdown_insert_content_extension/static/third-party-licenses.json
jupyterlab_markdown_insert_content_extension-1.1.15.data/data/share/jupyter/labextensions/jupyterlab_markdown_insert_content_extension/install.json
jupyterlab_markdown_insert_content_extension-1.1.15.dist-info/METADATA
jupyterlab_markdown_insert_content_extension-1.1.15.dist-info/WHEEL
jupyterlab_markdown_insert_content_extension-1.1.15.dist-info/licenses/LICENSE
jupyterlab_markdown_insert_content_extension-1.1.15.dist-info/RECORD
